drf_multitokenauth/__init__.py
drf_multitokenauth/admin.py
drf_multitokenauth/coreauthentication.py
drf_multitokenauth/models.py
drf_multitokenauth/serializers.py
drf_multitokenauth/signals.py
drf_multitokenauth/urls.py
drf_multitokenauth/views.py
drf_multitokenauth/migrations/0001_initial.py
drf_multitokenauth/migrations/0002_rename_ip_address_20160426.py
drf_multitokenauth/migrations/0003_pk_migration.py
drf_multitokenauth/migrations/0004_multitoken_name.py
drf_multitokenauth/migrations/__init__.py
drf_multitokenauth-2.1.0.dist-info/LICENSE
drf_multitokenauth-2.1.0.dist-info/METADATA
drf_multitokenauth-2.1.0.dist-info/WHEEL
drf_multitokenauth-2.1.0.dist-info/top_level.txt
drf_multitokenauth-2.1.0.dist-info/RECORD
